fflows/__init__.py
fflows/logger.py
fflows/sequential_flows.py
fflows/version.py
fflows/filters/__init__.py
fflows/filters/spectral.py
fflows/fourier/__init__.py
fflows/fourier/transforms.py
fflows/models/__init__.py
fflows/models/sequential.py
fflows/models/timegan.py
fflows/utils/__init__.py
fflows/utils/data_padding.py
fflows/utils/make_data.py
fflows/utils/misc.py
fflows/utils/spectral.py
fflows-0.0.3.dist-info/LICENSE
fflows-0.0.3.dist-info/METADATA
fflows-0.0.3.dist-info/WHEEL
fflows-0.0.3.dist-info/top_level.txt
fflows-0.0.3.dist-info/RECORD
