Metadata-Version: 2.1
Name: fflows
Version: 0.0.3
Summary: Generative Time-series Modeling with Fourier Flows
Home-page: https://github.com/vanderschaarlab/Fourier-flows
Author: Ahmed Alaa
License: BSD-3-Clause
Platform: UNKNOWN
Classifier: Programming Language :: Python :: 3
Classifier: Topic :: Scientific/Engineering :: Artificial Intelligence
Classifier: Intended Audience :: Healthcare Industry
Classifier: License :: OSI Approved :: BSD License
Classifier: Operating System :: OS Independent
Requires-Dist: numpy
Requires-Dist: scikit-learn
Requires-Dist: scipy
Requires-Dist: torch
Requires-Dist: loguru
